timeship/__init__.py
timeship/html_page.py
timeship/test.py
timeship/timeship.py
timeship-1.0.1.dist-info/LICENSE
timeship-1.0.1.dist-info/METADATA
timeship-1.0.1.dist-info/WHEEL
timeship-1.0.1.dist-info/top_level.txt
timeship-1.0.1.dist-info/RECORD
