Metadata-Version: 2.1
Name: timeship
Version: 1.0.1
Summary: Easy timing of all kinds of python code.
Home-page: https://git.rwth-aachen.de/dennis.noll/timeship.git
Author: Nollde
License: UNKNOWN
Platform: UNKNOWN
Classifier: Programming Language :: Python :: 3
Classifier: License :: OSI Approved :: MIT License
Classifier: Operating System :: OS Independent
Requires-Dist: numpy
